torchvisualizer/__init__.py
torchvisualizer/extractor.py
torchvisualizer/plotter.py
torchvisualizer/visualization.py
torchvisualizer-0.1.0.dist-info/METADATA
torchvisualizer-0.1.0.dist-info/WHEEL
torchvisualizer-0.1.0.dist-info/top_level.txt
torchvisualizer-0.1.0.dist-info/RECORD
