Metadata-Version: 2.4
Name: torchvisualizer
Version: 0.1.0
Summary: A utility for visualizing PyTorch model architectures.
Author: Vidit Gupta
Classifier: Programming Language :: Python :: 3
Classifier: Operating System :: OS Independent
Classifier: Topic :: Scientific/Engineering :: Visualization
Classifier: Topic :: Software Development :: Libraries :: Python Modules
Requires-Python: >=3.8
Requires-Dist: torch>=1.10.0
Requires-Dist: matplotlib>=3.5.0
Dynamic: author
Dynamic: classifier
Dynamic: description
Dynamic: description-content-type
Dynamic: requires-dist
Dynamic: requires-python
Dynamic: summary
